ground_assistant/__init__.py
ground_assistant/data.py
ground_assistant/load.py
ground_assistant/main.py
ground_assistant-1.0.4.dist-info/METADATA
ground_assistant-1.0.4.dist-info/WHEEL
ground_assistant-1.0.4.dist-info/top_level.txt
ground_assistant-1.0.4.dist-info/RECORD
